Workbook
Name Slicer_Category2: #N/A
Name Slicer_Customer_Type: #N/A
Name Slicer_Month1: #N/A
Name Slicer_Quarter: #N/A
Name Slicer_Region2: #N/A
Name Slicer_Salesperson1: #N/A

Sheet Original Data
A1: Order ID | B1: Date | C1: Salesperson | D1: Region | E1: Category | F1: Product Name | G1: Units Sold | H1: Unit Price (PKR) | I1: Discount % | J1: Total Revenue (PKR) | K1: Cost Price (Unit) | L1: Total Cost (PKR) | M1: Profit (PKR) | N1: Customer Type | O1: Payment Method | P1: Delivery Status
A2: ORD-1001 | B2: 2024-11-23 | C2: Sara Khan | D2: Karachi | E2: Home Appliances | F2: Iron | G2: 8 | H2: 3500 | I2: 5 | J2: 26600 | K2: 2000 | L2: 16000 | M2: 10600 | N2: New | O2: Bank Transfer | P2: Pending
A3: ORD-1002 | B3: 2024-10-06 | C3: Sara Khan | D3: Faisalabad | E3: Electronics | F3: Mobile Phone | G3: 3 | H3: 25000 | I3: 5 | J3: 71250 | K3: 18000 | L3: 54000 | M3: 17250 | N3: New | O3: EasyPaisa | P3: Pending
A4: ORD-1003 | B4: 2024-10-14 | C4: Fatima Malik | D4: Faisalabad | E4: Clothing | F4: Jacket | G4: 19 | H4: 6000 | I4: 10 | J4: 102600 | K4: 3500 | L4: 66500 | M4: 36100 | N4: New | O4: Credit Card | P4: Pending
A5: ORD-1004 | B5: 2024-06-23 | C5: Usman Raza | D5: Islamabad | E5: Clothing | F5: Jeans | G5: 4 | H5: 3000 | I5: 0 | J5: 12000 | K5: 1500 | L5: 6000 | M5: 6000 | N5: Returning | O5: Cash | P5: Delivered
A6: ORD-1005 | B6: 2024-06-25 | C6: Nadia Iqbal | D6: Quetta | E6: Electronics | F6: Headphones | G6: 18 | H6: 5000 | I6: 0 | J6: 90000 | K6: 3000 | L6: 54000 | M6: 36000 | N6: Returning | O6: Cash | P6: Delivered
A7: ORD-1006 | B7: 2024-11-17 | C7: Nadia Iqbal | D7: Multan | E7: Sports | F7: Football | G7: 3 | H7: 2000 | I7: 0 | J7: 6000 | K7: 1200 | L7: 3600 | M7: 2400 | N7: New | O7: Debit Card | P7: Returned
A8: ORD-1007 | B8: 2024-04-29 | C8: Sara Khan | D8: Faisalabad | E8: Home Appliances | F8: Air Fryer | G8: 12 | H8: 12000 | I8: 5 | J8: 136800 | K8: 8000 | L8: 96000 | M8: 40800 | N8: Returning | O8: Debit Card | P8: Delivered
A9: ORD-1008 | B9: 2024-05-16 | C9: Sara Khan | D9: Islamabad | E9: Sports | F9: Football | G9: 6 | H9: 2000 | I9: 15 | J9: 10200 | K9: 1200 | L9: 7200 | M9: 3000 | N9: Returning | O9: Debit Card | P9: Returned
A10: ORD-1009 | B10: 2024-11-23 | C10: Kamran Sheikh | D10: Peshawar | E10: Home Appliances | F10: Microwave | G10: 8 | H10: 18000 | I10: 0 | J10: 144000 | K10: 12000 | L10: 96000 | M10: 48000 | N10: Returning | O10: JazzCash | P10: Delivered
A11: ORD-1010 | B11: 2024-04-18 | C11: Nadia Iqbal | D11: Multan | E11: Clothing | F11: Jacket | G11: 13 | H11: 6000 | I11: 25 | J11: 58500 | K11: 3500 | L11: 45500 | M11: 13000 | N11: Returning | O11: Credit Card | P11: Delivered
A12: ORD-1011 | B12: 2024-05-06 | C12: Kamran Sheikh | D12: Quetta | E12: Sports | F12: Dumbbells Set | G12: 19 | H12: 8000 | I12: 15 | J12: 129200 | K12: 5000 | L12: 95000 | M12: 34200 | N12: Returning | O12: Credit Card | P12: Returned
A13: ORD-1012 | B13: 2024-03-11 | C13: Kamran Sheikh | D13: Rawalpindi | E13: Electronics | F13: Mobile Phone | G13: 4 | H13: 25000 | I13: 5 | J13: 95000 | K13: 18000 | L13: 72000 | M13: 23000 | N13: New | O13: Bank Transfer | P13: Delivered
... A501: ORD-1500 | B501: 2024-08-22 | C501: Zara Butt | D501: Karachi | E501: Groceries | F501: Rice 5kg | G501: 9 | H501: 800 | I501: 0 | J501: 7200 | K501: 600 | L501: 5400 | M501: 1800 | N501: Returning | O501: Bank Transfer | P501: Shipped

Sheet Cleaned Data
A1: Order ID | B1: Date | C1: Month | D1: Quarter | E1: Year | F1: Salesperson | G1: Region | H1: Category | I1: Product Name | J1: Units Sold | K1: Unit Price (PKR) | L1: Discount % | M1: Total Revenue (PKR) | N1: Profit Margin% | O1: Cost Price (Unit) | P1: Total Cost (PKR) | Q1: Profit (PKR) | R1: Customer Type | S1: Order Flag | T1: Payment Method | U1: Delivery Status | V1: Date2
A2: ORD-1001 | B2: =DATEVALUE(Table1[[#This Row],[Date2]]) -> 45619 | C2: =TEXT(Table1[[#This Row],[Date]],"MMM") -> Nov | D2: ="Q"&ROUNDUP(MONTH(Table1[[#This Row],[Date]])/3,0) -> Q4 | E2: =YEAR(Table1[[#This Row],[Date]]) -> 2024 | F2: Sara Khan | G2: Karachi | H2: Home Appliances | I2: Iron | J2: 8 | K2: 3500 | L2: 5 | M2: 26600 | N2: =(Table1[[#This Row],[Profit (PKR)]]/Table1[[#This Row],[Total Revenue (PKR)]]) -> 0.39849624 | O2: 2000 | P2: 16000 | Q2: 10600 | R2: New | S2: =IF(AND(Table1[[#This Row],[Total Revenue (PKR)]]>50000, Table1[[#This Row],[Discount %]]<10),"High Value","Standard") -> Standard | T2: Bank Transfer | U2: Pending | V2: 2024-11-23
A3: ORD-1002 | B3: =DATEVALUE(Table1[[#This Row],[Date2]]) -> 45571 | C3: =TEXT(Table1[[#This Row],[Date]],"MMM") -> Oct | D3: ="Q"&ROUNDUP(MONTH(Table1[[#This Row],[Date]])/3,0) -> Q4 | E3: =YEAR(Table1[[#This Row],[Date]]) -> 2024 | F3: Sara Khan | G3: Faisalabad | H3: Electronics | I3: Mobile Phone | J3: 3 | K3: 25000 | L3: 5 | M3: 71250 | N3: =(Table1[[#This Row],[Profit (PKR)]]/Table1[[#This Row],[Total Revenue (PKR)]]) -> 0.24210526 | O3: 18000 | P3: 54000 | Q3: 17250 | R3: New | S3: =IF(AND(Table1[[#This Row],[Total Revenue (PKR)]]>50000, Table1[[#This Row],[Discount %]]<10),"High Value","Standard") -> High Value | T3: EasyPaisa | U3: Pending | V3: 2024-10-06
A4: ORD-1003 | B4: =DATEVALUE(Table1[[#This Row],[Date2]]) -> 45579 | C4: =TEXT(Table1[[#This Row],[Date]],"MMM") -> Oct | D4: ="Q"&ROUNDUP(MONTH(Table1[[#This Row],[Date]])/3,0) -> Q4 | E4: =YEAR(Table1[[#This Row],[Date]]) -> 2024 | F4: Fatima Malik | G4: Faisalabad | H4: Clothing | I4: Jacket | J4: 19 | K4: 6000 | L4: 10 | M4: 102600 | N4: =(Table1[[#This Row],[Profit (PKR)]]/Table1[[#This Row],[Total Revenue (PKR)]]) -> 0.35185185 | O4: 3500 | P4: 66500 | Q4: 36100 | R4: New | S4: =IF(AND(Table1[[#This Row],[Total Revenue (PKR)]]>50000, Table1[[#This Row],[Discount %]]<10),"High Value","Standard") -> Standard | T4: Credit Card | U4: Pending | V4: 2024-10-14
A5: ORD-1004 | B5: =DATEVALUE(Table1[[#This Row],[Date2]]) -> 45466 | C5: =TEXT(Table1[[#This Row],[Date]],"MMM") -> Jun | D5: ="Q"&ROUNDUP(MONTH(Table1[[#This Row],[Date]])/3,0) -> Q2 | E5: =YEAR(Table1[[#This Row],[Date]]) -> 2024 | F5: Usman Raza | G5: Islamabad | H5: Clothing | I5: Jeans | J5: 4 | K5: 3000 | L5: 0 | M5: 12000 | N5: =(Table1[[#This Row],[Profit (PKR)]]/Table1[[#This Row],[Total Revenue (PKR)]]) -> 0.5 | O5: 1500 | P5: 6000 | Q5: 6000 | R5: Returning | S5: =IF(AND(Table1[[#This Row],[Total Revenue (PKR)]]>50000, Table1[[#This Row],[Discount %]]<10),"High Value","Standard") -> Standard | T5: Cash | U5: Delivered | V5: 2024-06-23
A6: ORD-1005 | B6: =DATEVALUE(Table1[[#This Row],[Date2]]) -> 45468 | C6: =TEXT(Table1[[#This Row],[Date]],"MMM") -> Jun | D6: ="Q"&ROUNDUP(MONTH(Table1[[#This Row],[Date]])/3,0) -> Q2 | E6: =YEAR(Table1[[#This Row],[Date]]) -> 2024 | F6: Nadia Iqbal | G6: Quetta | H6: Electronics | I6: Headphones | J6: 18 | K6: 5000 | L6: 0 | M6: 90000 | N6: =(Table1[[#This Row],[Profit (PKR)]]/Table1[[#This Row],[Total Revenue (PKR)]]) -> 0.4 | O6: 3000 | P6: 54000 | Q6: 36000 | R6: Returning | S6: =IF(AND(Table1[[#This Row],[Total Revenue (PKR)]]>50000, Table1[[#This Row],[Discount %]]<10),"High Value","Standard") -> High Value | T6: Cash | U6: Delivered | V6: 2024-06-25
A7: ORD-1006 | B7: =DATEVALUE(Table1[[#This Row],[Date2]]) -> 45613 | C7: =TEXT(Table1[[#This Row],[Date]],"MMM") -> Nov | D7: ="Q"&ROUNDUP(MONTH(Table1[[#This Row],[Date]])/3,0) -> Q4 | E7: =YEAR(Table1[[#This Row],[Date]]) -> 2024 | F7: Nadia Iqbal | G7: Multan | H7: Sports | I7: Football | J7: 3 | K7: 2000 | L7: 0 | M7: 6000 | N7: =(Table1[[#This Row],[Profit (PKR)]]/Table1[[#This Row],[Total Revenue (PKR)]]) -> 0.4 | O7: 1200 | P7: 3600 | Q7: 2400 | R7: New | S7: =IF(AND(Table1[[#This Row],[Total Revenue (PKR)]]>50000, Table1[[#This Row],[Discount %]]<10),"High Value","Standard") -> Standard | T7: Debit Card | U7: Returned | V7: 2024-11-17
A8: ORD-1007 | B8: =DATEVALUE(Table1[[#This Row],[Date2]]) -> 45411 | C8: =TEXT(Table1[[#This Row],[Date]],"MMM") -> Apr | D8: ="Q"&ROUNDUP(MONTH(Table1[[#This Row],[Date]])/3,0) -> Q2 | E8: =YEAR(Table1[[#This Row],[Date]]) -> 2024 | F8: Sara Khan | G8: Faisalabad | H8: Home Appliances | I8: Air Fryer | J8: 12 | K8: 12000 | L8: 5 | M8: 136800 | N8: =(Table1[[#This Row],[Profit (PKR)]]/Table1[[#This Row],[Total Revenue (PKR)]]) -> 0.29824561 | O8: 8000 | P8: 96000 | Q8: 40800 | R8: Returning | S8: =IF(AND(Table1[[#This Row],[Total Revenue (PKR)]]>50000, Table1[[#This Row],[Discount %]]<10),"High Value","Standard") -> High Value | T8: Debit Card | U8: Delivered | V8: 2024-04-29
A9: ORD-1008 | B9: =DATEVALUE(Table1[[#This Row],[Date2]]) -> 45428 | C9: =TEXT(Table1[[#This Row],[Date]],"MMM") -> May | D9: ="Q"&ROUNDUP(MONTH(Table1[[#This Row],[Date]])/3,0) -> Q2 | E9: =YEAR(Table1[[#This Row],[Date]]) -> 2024 | F9: Sara Khan | G9: Islamabad | H9: Sports | I9: Football | J9: 6 | K9: 2000 | L9: 15 | M9: 10200 | N9: =(Table1[[#This Row],[Profit (PKR)]]/Table1[[#This Row],[Total Revenue (PKR)]]) -> 0.29411765 | O9: 1200 | P9: 7200 | Q9: 3000 | R9: Returning | S9: =IF(AND(Table1[[#This Row],[Total Revenue (PKR)]]>50000, Table1[[#This Row],[Discount %]]<10),"High Value","Standard") -> Standard | T9: Debit Card | U9: Returned | V9: 2024-05-16
A10: ORD-1009 | B10: =DATEVALUE(Table1[[#This Row],[Date2]]) -> 45619 | C10: =TEXT(Table1[[#This Row],[Date]],"MMM") -> Nov | D10: ="Q"&ROUNDUP(MONTH(Table1[[#This Row],[Date]])/3,0) -> Q4 | E10: =YEAR(Table1[[#This Row],[Date]]) -> 2024 | F10: Kamran Sheikh | G10: Peshawar | H10: Home Appliances | I10: Microwave | J10: 8 | K10: 18000 | L10: 0 | M10: 144000 | N10: =(Table1[[#This Row],[Profit (PKR)]]/Table1[[#This Row],[Total Revenue (PKR)]]) -> 0.33333333 | O10: 12000 | P10: 96000 | Q10: 48000 | R10: Returning | S10: =IF(AND(Table1[[#This Row],[Total Revenue (PKR)]]>50000, Table1[[#This Row],[Discount %]]<10),"High Value","Standard") -> High Value | T10: JazzCash | U10: Delivered | V10: 2024-11-23
A11: ORD-1010 | B11: =DATEVALUE(Table1[[#This Row],[Date2]]) -> 45400 | C11: =TEXT(Table1[[#This Row],[Date]],"MMM") -> Apr | D11: ="Q"&ROUNDUP(MONTH(Table1[[#This Row],[Date]])/3,0) -> Q2 | E11: =YEAR(Table1[[#This Row],[Date]]) -> 2024 | F11: Nadia Iqbal | G11: Multan | H11: Clothing | I11: Jacket | J11: 13 | K11: 6000 | L11: 25 | M11: 58500 | N11: =(Table1[[#This Row],[Profit (PKR)]]/Table1[[#This Row],[Total Revenue (PKR)]]) -> 0.22222222 | O11: 3500 | P11: 45500 | Q11: 13000 | R11: Returning | S11: =IF(AND(Table1[[#This Row],[Total Revenue (PKR)]]>50000, Table1[[#This Row],[Discount %]]<10),"High Value","Standard") -> Standard | T11: Credit Card | U11: Delivered | V11: 2024-04-18
A12: ORD-1011 | B12: =DATEVALUE(Table1[[#This Row],[Date2]]) -> 45418 | C12: =TEXT(Table1[[#This Row],[Date]],"MMM") -> May | D12: ="Q"&ROUNDUP(MONTH(Table1[[#This Row],[Date]])/3,0) -> Q2 | E12: =YEAR(Table1[[#This Row],[Date]]) -> 2024 | F12: Kamran Sheikh | G12: Quetta | H12: Sports | I12: Dumbbells Set | J12: 19 | K12: 8000 | L12: 15 | M12: 129200 | N12: =(Table1[[#This Row],[Profit (PKR)]]/Table1[[#This Row],[Total Revenue (PKR)]]) -> 0.26470588 | O12: 5000 | P12: 95000 | Q12: 34200 | R12: Returning | S12: =IF(AND(Table1[[#This Row],[Total Revenue (PKR)]]>50000, Table1[[#This Row],[Discount %]]<10),"High Value","Standard") -> Standard | T12: Credit Card | U12: Returned | V12: 2024-05-06
A13: ORD-1012 | B13: =DATEVALUE(Table1[[#This Row],[Date2]]) -> 45362 | C13: =TEXT(Table1[[#This Row],[Date]],"MMM") -> Mar | D13: ="Q"&ROUNDUP(MONTH(Table1[[#This Row],[Date]])/3,0) -> Q1 | E13: =YEAR(Table1[[#This Row],[Date]]) -> 2024 | F13: Kamran Sheikh | G13: Rawalpindi | H13: Electronics | I13: Mobile Phone | J13: 4 | K13: 25000 | L13: 5 | M13: 95000 | N13: =(Table1[[#This Row],[Profit (PKR)]]/Table1[[#This Row],[Total Revenue (PKR)]]) -> 0.24210526 | O13: 18000 | P13: 72000 | Q13: 23000 | R13: New | S13: =IF(AND(Table1[[#This Row],[Total Revenue (PKR)]]>50000, Table1[[#This Row],[Discount %]]<10),"High Value","Standard") -> High Value | T13: Bank Transfer | U13: Delivered | V13: 2024-03-11
... A501: ORD-1500 | B501: =DATEVALUE(Table1[[#This Row],[Date2]]) -> 45526 | C501: =TEXT(Table1[[#This Row],[Date]],"MMM") -> Aug | D501: ="Q"&ROUNDUP(MONTH(Table1[[#This Row],[Date]])/3,0) -> Q3 | E501: =YEAR(Table1[[#This Row],[Date]]) -> 2024 | F501: Zara Butt | G501: Karachi | H501: Groceries | I501: Rice 5kg | J501: 9 | K501: 800 | L501: 0 | M501: 7200 | N501: =(Table1[[#This Row],[Profit (PKR)]]/Table1[[#This Row],[Total Revenue (PKR)]]) -> 0.25 | O501: 600 | P501: 5400 | Q501: 1800 | R501: Returning | S501: =IF(AND(Table1[[#This Row],[Total Revenue (PKR)]]>50000, Table1[[#This Row],[Discount %]]<10),"High Value","Standard") -> Standard | T501: Bank Transfer | U501: Shipped | V501: 2024-08-22
M502: =SUBTOTAL(109,Table1[Total Revenue (PKR)]) -> 52968740 | N502: =AVERAGE(Table1[Profit Margin%]) -> 0.26039038 | Q502: =SUM(Table1[Profit (PKR)]) -> 9129880 | V502: =SUBTOTAL(109,Table1[Date2]) -> 0

Sheet Formulas & Analysis
D4: Salesperson | E4: Total Revenue | F4: Total Profit | G4: No.of Orders | H4: Avg Discount | I4: Delivered(#) | K4: Salesperson | L4: Total Profit | M4: Rank
D5: Ahmed Ali | E5: =SUMIFS('Cleaned Data'!M:M,'Cleaned Data'!F:F,Table2[[#This Row],[Salesperson]]) -> 4096660 | F5: =SUMIFS('Cleaned Data'!Q:Q,'Cleaned Data'!F:F,Table2[[#This Row],[Salesperson]]) -> 791960 | G5: =COUNTIFS('Cleaned Data'!F:F,Table2[[#This Row],[Salesperson]]) -> 46 | H5: =AVERAGEIFS('Cleaned Data'!L:L,'Cleaned Data'!F:F,Table2[[#This Row],[Salesperson]]) -> 11.195652 | I5: =COUNTIFS('Cleaned Data'!F:F,Table2[[#This Row],[Salesperson]],'Cleaned Data'!U:U,"Delivered") -> 29 | K5: Ahmed Ali | L5: =SUMIFS('Cleaned Data'!Q:Q,'Cleaned Data'!F:F,Table6[[#This Row],[Salesperson]]) -> 791960 | M5: =RANK(Table6[[#This Row],[Total Profit]],Table6[Total Profit],0) -> 5
D6: Ayesha Siddiqui | E6: =SUMIFS('Cleaned Data'!M:M,'Cleaned Data'!F:F,Table2[[#This Row],[Salesperson]]) -> 6054305 | F6: =SUMIFS('Cleaned Data'!Q:Q,'Cleaned Data'!F:F,Table2[[#This Row],[Salesperson]]) -> 710145 | G6: =COUNTIFS('Cleaned Data'!F:F,Table2[[#This Row],[Salesperson]]) -> 52 | H6: =AVERAGEIFS('Cleaned Data'!L:L,'Cleaned Data'!F:F,Table2[[#This Row],[Salesperson]]) -> 14.519231 | I6: =COUNTIFS('Cleaned Data'!F:F,Table2[[#This Row],[Salesperson]],'Cleaned Data'!U:U,"Delivered") -> 32 | K6: Ayesha Siddiqui | L6: =SUMIFS('Cleaned Data'!Q:Q,'Cleaned Data'!F:F,Table6[[#This Row],[Salesperson]]) -> 710145 | M6: =RANK(Table6[[#This Row],[Total Profit]],Table6[Total Profit],0) -> 8
D7: Bilal Hussain | E7: =SUMIFS('Cleaned Data'!M:M,'Cleaned Data'!F:F,Table2[[#This Row],[Salesperson]]) -> 8698130 | F7: =SUMIFS('Cleaned Data'!Q:Q,'Cleaned Data'!F:F,Table2[[#This Row],[Salesperson]]) -> 1459910 | G7: =COUNTIFS('Cleaned Data'!F:F,Table2[[#This Row],[Salesperson]]) -> 55 | H7: =AVERAGEIFS('Cleaned Data'!L:L,'Cleaned Data'!F:F,Table2[[#This Row],[Salesperson]]) -> 14.181818 | I7: =COUNTIFS('Cleaned Data'!F:F,Table2[[#This Row],[Salesperson]],'Cleaned Data'!U:U,"Delivered") -> 28 | K7: Bilal Hussain | L7: =SUMIFS('Cleaned Data'!Q:Q,'Cleaned Data'!F:F,Table6[[#This Row],[Salesperson]]) -> 1459910 | M7: =RANK(Table6[[#This Row],[Total Profit]],Table6[Total Profit],0) -> 1
D8: Fatima Malik | E8: =SUMIFS('Cleaned Data'!M:M,'Cleaned Data'!F:F,Table2[[#This Row],[Salesperson]]) -> 5657955 | F8: =SUMIFS('Cleaned Data'!Q:Q,'Cleaned Data'!F:F,Table2[[#This Row],[Salesperson]]) -> 718855 | G8: =COUNTIFS('Cleaned Data'!F:F,Table2[[#This Row],[Salesperson]]) -> 45 | H8: =AVERAGEIFS('Cleaned Data'!L:L,'Cleaned Data'!F:F,Table2[[#This Row],[Salesperson]]) -> 12.444444 | I8: =COUNTIFS('Cleaned Data'!F:F,Table2[[#This Row],[Salesperson]],'Cleaned Data'!U:U,"Delivered") -> 24 | K8: Fatima Malik | L8: =SUMIFS('Cleaned Data'!Q:Q,'Cleaned Data'!F:F,Table6[[#This Row],[Salesperson]]) -> 718855 | M8: =RANK(Table6[[#This Row],[Total Profit]],Table6[Total Profit],0) -> 7
D9: Hassan Mirza | E9: =SUMIFS('Cleaned Data'!M:M,'Cleaned Data'!F:F,Table2[[#This Row],[Salesperson]]) -> 2606325 | F9: =SUMIFS('Cleaned Data'!Q:Q,'Cleaned Data'!F:F,Table2[[#This Row],[Salesperson]]) -> 679465 | G9: =COUNTIFS('Cleaned Data'!F:F,Table2[[#This Row],[Salesperson]]) -> 41 | H9: =AVERAGEIFS('Cleaned Data'!L:L,'Cleaned Data'!F:F,Table2[[#This Row],[Salesperson]]) -> 13.902439 | I9: =COUNTIFS('Cleaned Data'!F:F,Table2[[#This Row],[Salesperson]],'Cleaned Data'!U:U,"Delivered") -> 22 | K9: Hassan Mirza | L9: =SUMIFS('Cleaned Data'!Q:Q,'Cleaned Data'!F:F,Table6[[#This Row],[Salesperson]]) -> 679465 | M9: =RANK(Table6[[#This Row],[Total Profit]],Table6[Total Profit],0) -> 9
D10: Kamran Sheikh | E10: =SUMIFS('Cleaned Data'!M:M,'Cleaned Data'!F:F,Table2[[#This Row],[Salesperson]]) -> 3035075 | F10: =SUMIFS('Cleaned Data'!Q:Q,'Cleaned Data'!F:F,Table2[[#This Row],[Salesperson]]) -> 754675 | G10: =COUNTIFS('Cleaned Data'!F:F,Table2[[#This Row],[Salesperson]]) -> 49 | H10: =AVERAGEIFS('Cleaned Data'!L:L,'Cleaned Data'!F:F,Table2[[#This Row],[Salesperson]]) -> 12.346939 | I10: =COUNTIFS('Cleaned Data'!F:F,Table2[[#This Row],[Salesperson]],'Cleaned Data'!U:U,"Delivered") -> 35 | K10: Kamran Sheikh | L10: =SUMIFS('Cleaned Data'!Q:Q,'Cleaned Data'!F:F,Table6[[#This Row],[Salesperson]]) -> 754675 | M10: =RANK(Table6[[#This Row],[Total Profit]],Table6[Total Profit],0) -> 6
D11: Nadia Iqbal | E11: =SUMIFS('Cleaned Data'!M:M,'Cleaned Data'!F:F,Table2[[#This Row],[Salesperson]]) -> 7225110 | F11: =SUMIFS('Cleaned Data'!Q:Q,'Cleaned Data'!F:F,Table2[[#This Row],[Salesperson]]) -> 1346610 | G11: =COUNTIFS('Cleaned Data'!F:F,Table2[[#This Row],[Salesperson]]) -> 66 | H11: =AVERAGEIFS('Cleaned Data'!L:L,'Cleaned Data'!F:F,Table2[[#This Row],[Salesperson]]) -> 12.424242 | I11: =COUNTIFS('Cleaned Data'!F:F,Table2[[#This Row],[Salesperson]],'Cleaned Data'!U:U,"Delivered") -> 39 | K11: Nadia Iqbal | L11: =SUMIFS('Cleaned Data'!Q:Q,'Cleaned Data'!F:F,Table6[[#This Row],[Salesperson]]) -> 1346610 | M11: =RANK(Table6[[#This Row],[Total Profit]],Table6[Total Profit],0) -> 2
D12: Sara Khan | E12: =SUMIFS('Cleaned Data'!M:M,'Cleaned Data'!F:F,Table2[[#This Row],[Salesperson]]) -> 6046970 | F12: =SUMIFS('Cleaned Data'!Q:Q,'Cleaned Data'!F:F,Table2[[#This Row],[Salesperson]]) -> 874050 | G12: =COUNTIFS('Cleaned Data'!F:F,Table2[[#This Row],[Salesperson]]) -> 58 | H12: =AVERAGEIFS('Cleaned Data'!L:L,'Cleaned Data'!F:F,Table2[[#This Row],[Salesperson]]) -> 12.844828 | I12: =COUNTIFS('Cleaned Data'!F:F,Table2[[#This Row],[Salesperson]],'Cleaned Data'!U:U,"Delivered") -> 33 | K12: Sara Khan | L12: =SUMIFS('Cleaned Data'!Q:Q,'Cleaned Data'!F:F,Table6[[#This Row],[Salesperson]]) -> 874050 | M12: =RANK(Table6[[#This Row],[Total Profit]],Table6[Total Profit],0) -> 4
D13: Usman Raza | E13: =SUMIFS('Cleaned Data'!M:M,'Cleaned Data'!F:F,Table2[[#This Row],[Salesperson]]) -> 4379865 | F13: =SUMIFS('Cleaned Data'!Q:Q,'Cleaned Data'!F:F,Table2[[#This Row],[Salesperson]]) -> 633765 | G13: =COUNTIFS('Cleaned Data'!F:F,Table2[[#This Row],[Salesperson]]) -> 45 | H13: =AVERAGEIFS('Cleaned Data'!L:L,'Cleaned Data'!F:F,Table2[[#This Row],[Salesperson]]) -> 13.333333 | I13: =COUNTIFS('Cleaned Data'!F:F,Table2[[#This Row],[Salesperson]],'Cleaned Data'!U:U,"Delivered") -> 21 | K13: Usman Raza | L13: =SUMIFS('Cleaned Data'!Q:Q,'Cleaned Data'!F:F,Table6[[#This Row],[Salesperson]]) -> 633765 | M13: =RANK(Table6[[#This Row],[Total Profit]],Table6[Total Profit],0) -> 10
D14: Zara Butt | E14: =SUMIFS('Cleaned Data'!M:M,'Cleaned Data'!F:F,Table2[[#This Row],[Salesperson]]) -> 5168345 | F14: =SUMIFS('Cleaned Data'!Q:Q,'Cleaned Data'!F:F,Table2[[#This Row],[Salesperson]]) -> 1160445 | G14: =COUNTIFS('Cleaned Data'!F:F,Table2[[#This Row],[Salesperson]]) -> 43 | H14: =AVERAGEIFS('Cleaned Data'!L:L,'Cleaned Data'!F:F,Table2[[#This Row],[Salesperson]]) -> 10 | I14: =COUNTIFS('Cleaned Data'!F:F,Table2[[#This Row],[Salesperson]],'Cleaned Data'!U:U,"Delivered") -> 27 | K14: Zara Butt | L14: =SUMIFS('Cleaned Data'!Q:Q,'Cleaned Data'!F:F,Table6[[#This Row],[Salesperson]]) -> 1160445 | M14: =RANK(Table6[[#This Row],[Total Profit]],Table6[Total Profit],0) -> 3
D18: Total Revenue | E18: =Table1[[#Totals],[Total Revenue (PKR)]] -> 52968740 | F18: Region | G18: Total Revenue | H18: Total Profit | I18: Avg Profit Margin | K18: Customer Type | L18: Total Revenue | M18: Avg Order Value
F19: Quetta | G19: =SUMIFS('Cleaned Data'!M:M,'Cleaned Data'!G:G,Table3[[#This Row],[Region]]) -> 5230650 | H19: =SUMIFS('Cleaned Data'!Q:Q,'Cleaned Data'!G:G,'Formulas & Analysis'!F22) -> 1011110 | I19: =AVERAGEIFS('Cleaned Data'!N:N,'Cleaned Data'!G:G,Table3[[#This Row],[Region]]) -> 0.26246489 | K19: New | L19: =SUMIFS('Cleaned Data'!M:M,'Cleaned Data'!R:R,Table5[[#This Row],[Customer Type]]) -> 26805285 | M19: =AVERAGEIFS('Cleaned Data'!M:M,'Cleaned Data'!R:R,Table5[[#This Row],[Customer Type]]) -> 109857.73
F20: Peshawar | G20: =SUMIFS('Cleaned Data'!M:M,'Cleaned Data'!G:G,Table3[[#This Row],[Region]]) -> 5312700 | H20: =SUMIFS('Cleaned Data'!Q:Q,'Cleaned Data'!G:G,'Formulas & Analysis'!F24) -> 1118915 | I20: =AVERAGEIFS('Cleaned Data'!N:N,'Cleaned Data'!G:G,Table3[[#This Row],[Region]]) -> 0.26625577 | K20: Returning | L20: =SUMIFS('Cleaned Data'!M:M,'Cleaned Data'!R:R,Table5[[#This Row],[Customer Type]]) -> 26163455 | M20: =AVERAGEIFS('Cleaned Data'!M:M,'Cleaned Data'!R:R,Table5[[#This Row],[Customer Type]]) -> 102201
D21: Total Profit | E21: =Table1[[#Totals],[Profit (PKR)]] -> 9129880 | F21: Faisalabad | G21: =SUMIFS('Cleaned Data'!M:M,'Cleaned Data'!G:G,Table3[[#This Row],[Region]]) -> 5745085 | H21: =SUMIFS('Cleaned Data'!Q:Q,'Cleaned Data'!G:G,'Formulas & Analysis'!F20) -> 1268240 | I21: =AVERAGEIFS('Cleaned Data'!N:N,'Cleaned Data'!G:G,Table3[[#This Row],[Region]]) -> 0.27157365
F22: Rawalpindi | G22: =SUMIFS('Cleaned Data'!M:M,'Cleaned Data'!G:G,Table3[[#This Row],[Region]]) -> 6559530 | H22: =SUMIFS('Cleaned Data'!Q:Q,'Cleaned Data'!G:G,'Formulas & Analysis'!F25) -> 1374925 | I22: =AVERAGEIFS('Cleaned Data'!N:N,'Cleaned Data'!G:G,Table3[[#This Row],[Region]]) -> 0.25538917
F23: Multan | G23: =SUMIFS('Cleaned Data'!M:M,'Cleaned Data'!G:G,Table3[[#This Row],[Region]]) -> 6952720 | H23: =SUMIFS('Cleaned Data'!Q:Q,'Cleaned Data'!G:G,'Formulas & Analysis'!F23) -> 1337400 | I23: =AVERAGEIFS('Cleaned Data'!N:N,'Cleaned Data'!G:G,Table3[[#This Row],[Region]]) -> 0.24256477
D24: AVG Profit Margin | E24: =Table1[[#Totals],[Profit Margin%]] -> 0.26039038 | F24: Karachi | G24: =SUMIFS('Cleaned Data'!M:M,'Cleaned Data'!G:G,Table3[[#This Row],[Region]]) -> 7566335 | H24: =SUMIFS('Cleaned Data'!Q:Q,'Cleaned Data'!G:G,'Formulas & Analysis'!F19) -> 951930 | I24: =AVERAGEIFS('Cleaned Data'!N:N,'Cleaned Data'!G:G,Table3[[#This Row],[Region]]) -> 0.26820877
F25: Islamabad | G25: =SUMIFS('Cleaned Data'!M:M,'Cleaned Data'!G:G,Table3[[#This Row],[Region]]) -> 7690565 | H25: =SUMIFS('Cleaned Data'!Q:Q,'Cleaned Data'!G:G,'Formulas & Analysis'!F21) -> 1079205 | I25: =AVERAGEIFS('Cleaned Data'!N:N,'Cleaned Data'!G:G,Table3[[#This Row],[Region]]) -> 0.26937131 | K25: Assumption | L25: Value | M25: Additional Profit
F26: Lahore | G26: =SUMIFS('Cleaned Data'!M:M,'Cleaned Data'!G:G,Table3[[#This Row],[Region]]) -> 7911155 | H26: =SUMIFS('Cleaned Data'!Q:Q,'Cleaned Data'!G:G,'Formulas & Analysis'!F26) -> 988155 | I26: =AVERAGEIFS('Cleaned Data'!N:N,'Cleaned Data'!G:G,Table3[[#This Row],[Region]]) -> 0.24215198 | K26: Discount Reduction | L26: 0.05 | M26: =SUM(Table1[Total Revenue (PKR)])*Table7[Value] -> 2648437
B29: Categories | C29: JAN | D29: Feb | E29: MAR | F29: APR | G29: MAY | H29: JUN | I29: JUL | J29: AUG | K29: SEP | L29: OCT | M29: NOV | N29: DEC | O29: REVENUE
B30: Home Appliances | C30: =SUMIFS('Cleaned Data'!$M:$M,'Cleaned Data'!$C:$C,C$29,'Cleaned Data'!$H:$H,$B30) -> 518100 | D30: =SUMIFS('Cleaned Data'!$M:$M,'Cleaned Data'!$H:$H,$B30,'Cleaned Data'!$C:$C,D$29) -> 1214250 | E30: =SUMIFS('Cleaned Data'!$M:$M,'Cleaned Data'!$H:$H,$B30,'Cleaned Data'!$C:$C,E$29) -> 896250 | F30: =SUMIFS('Cleaned Data'!$M:$M,'Cleaned Data'!$H:$H,$B30,'Cleaned Data'!$C:$C,F$29) -> 268725 | G30: =SUMIFS('Cleaned Data'!$M:$M,'Cleaned Data'!$H:$H,$B30,'Cleaned Data'!$C:$C,G$29) -> 472500 | H30: =SUMIFS('Cleaned Data'!$M:$M,'Cleaned Data'!$H:$H,$B30,'Cleaned Data'!$C:$C,H$29) -> 1902750 | I30: =SUMIFS('Cleaned Data'!$M:$M,'Cleaned Data'!$H:$H,$B30,'Cleaned Data'!$C:$C,I$29) -> 1168500 | J30: =SUMIFS('Cleaned Data'!$M:$M,'Cleaned Data'!$H:$H,$B30,'Cleaned Data'!$C:$C,J$29) -> 1189650 | K30: =SUMIFS('Cleaned Data'!$M:$M,'Cleaned Data'!$H:$H,$B30,'Cleaned Data'!$C:$C,K$29) -> 1451400 | ... N30: =SUMIFS('Cleaned Data'!$M:$M,'Cleaned Data'!$H:$H,$B30,'Cleaned Data'!$C:$C,N$29) -> 964375 | O30: =SUM(Table8[[#This Row],[JAN]:[DEC]]) -> 12344050
B31: Electronics | C31: =SUMIFS('Cleaned Data'!M:M,'Cleaned Data'!C:C,C$29,'Cleaned Data'!H:H,$B31) -> 1320000 | D31: =SUMIFS('Cleaned Data'!$M:$M,'Cleaned Data'!$H:$H,$B31,'Cleaned Data'!$C:$C,D$29) -> 1092750 | E31: =SUMIFS('Cleaned Data'!$M:$M,'Cleaned Data'!$H:$H,$B31,'Cleaned Data'!$C:$C,E$29) -> 4213000 | F31: =SUMIFS('Cleaned Data'!$M:$M,'Cleaned Data'!$H:$H,$B31,'Cleaned Data'!$C:$C,F$29) -> 3602500 | G31: =SUMIFS('Cleaned Data'!$M:$M,'Cleaned Data'!$H:$H,$B31,'Cleaned Data'!$C:$C,G$29) -> 4013500 | H31: =SUMIFS('Cleaned Data'!$M:$M,'Cleaned Data'!$H:$H,$B31,'Cleaned Data'!$C:$C,H$29) -> 1304500 | I31: =SUMIFS('Cleaned Data'!$M:$M,'Cleaned Data'!$H:$H,$B31,'Cleaned Data'!$C:$C,I$29) -> 2040000 | J31: =SUMIFS('Cleaned Data'!$M:$M,'Cleaned Data'!$H:$H,$B31,'Cleaned Data'!$C:$C,J$29) -> 2193500 | K31: =SUMIFS('Cleaned Data'!$M:$M,'Cleaned Data'!$H:$H,$B31,'Cleaned Data'!$C:$C,K$29) -> 4219500 | ... N31: =SUMIFS('Cleaned Data'!$M:$M,'Cleaned Data'!$H:$H,$B31,'Cleaned Data'!$C:$C,N$29) -> 3896000 | O31: =SUM(Table8[[#This Row],[JAN]:[DEC]]) -> 33322000
B32: Clothing | C32: =SUMIFS('Cleaned Data'!M:M,'Cleaned Data'!C:C,C$29,'Cleaned Data'!H:H,$B32) -> 228975 | D32: =SUMIFS('Cleaned Data'!$M:$M,'Cleaned Data'!$H:$H,$B32,'Cleaned Data'!$C:$C,D$29) -> 239000 | E32: =SUMIFS('Cleaned Data'!$M:$M,'Cleaned Data'!$H:$H,$B32,'Cleaned Data'!$C:$C,E$29) -> 202325 | F32: =SUMIFS('Cleaned Data'!$M:$M,'Cleaned Data'!$H:$H,$B32,'Cleaned Data'!$C:$C,F$29) -> 162425 | G32: =SUMIFS('Cleaned Data'!$M:$M,'Cleaned Data'!$H:$H,$B32,'Cleaned Data'!$C:$C,G$29) -> 350075 | H32: =SUMIFS('Cleaned Data'!$M:$M,'Cleaned Data'!$H:$H,$B32,'Cleaned Data'!$C:$C,H$29) -> 509625 | I32: =SUMIFS('Cleaned Data'!$M:$M,'Cleaned Data'!$H:$H,$B32,'Cleaned Data'!$C:$C,I$29) -> 605175 | J32: =SUMIFS('Cleaned Data'!$M:$M,'Cleaned Data'!$H:$H,$B32,'Cleaned Data'!$C:$C,J$29) -> 232400 | K32: =SUMIFS('Cleaned Data'!$M:$M,'Cleaned Data'!$H:$H,$B32,'Cleaned Data'!$C:$C,K$29) -> 282325 | ... N32: =SUMIFS('Cleaned Data'!$M:$M,'Cleaned Data'!$H:$H,$B32,'Cleaned Data'!$C:$C,N$29) -> 147075 | O32: =SUM(Table8[[#This Row],[JAN]:[DEC]]) -> 3323600
B33: Sports | C33: =SUMIFS('Cleaned Data'!M:M,'Cleaned Data'!C:C,C$29,'Cleaned Data'!H:H,$B33) -> 366900 | D33: =SUMIFS('Cleaned Data'!$M:$M,'Cleaned Data'!$H:$H,$B33,'Cleaned Data'!$C:$C,D$29) -> 492780 | E33: =SUMIFS('Cleaned Data'!$M:$M,'Cleaned Data'!$H:$H,$B33,'Cleaned Data'!$C:$C,E$29) -> 112520 | F33: =SUMIFS('Cleaned Data'!$M:$M,'Cleaned Data'!$H:$H,$B33,'Cleaned Data'!$C:$C,F$29) -> 208515 | G33: =SUMIFS('Cleaned Data'!$M:$M,'Cleaned Data'!$H:$H,$B33,'Cleaned Data'!$C:$C,G$29) -> 535470 | H33: =SUMIFS('Cleaned Data'!$M:$M,'Cleaned Data'!$H:$H,$B33,'Cleaned Data'!$C:$C,H$29) -> 273820 | I33: =SUMIFS('Cleaned Data'!$M:$M,'Cleaned Data'!$H:$H,$B33,'Cleaned Data'!$C:$C,I$29) -> 277900 | J33: =SUMIFS('Cleaned Data'!$M:$M,'Cleaned Data'!$H:$H,$B33,'Cleaned Data'!$C:$C,J$29) -> 300575 | K33: =SUMIFS('Cleaned Data'!$M:$M,'Cleaned Data'!$H:$H,$B33,'Cleaned Data'!$C:$C,K$29) -> 56340 | ... N33: =SUMIFS('Cleaned Data'!$M:$M,'Cleaned Data'!$H:$H,$B33,'Cleaned Data'!$C:$C,N$29) -> 316160 | O33: =SUM(Table8[[#This Row],[JAN]:[DEC]]) -> 3124595
B34: Groceries | C34: =SUMIFS('Cleaned Data'!M:M,'Cleaned Data'!C:C,C$29,'Cleaned Data'!H:H,$B34) -> 26720 | D34: =SUMIFS('Cleaned Data'!$M:$M,'Cleaned Data'!$H:$H,$B34,'Cleaned Data'!$C:$C,D$29) -> 93505 | E34: =SUMIFS('Cleaned Data'!$M:$M,'Cleaned Data'!$H:$H,$B34,'Cleaned Data'!$C:$C,E$29) -> 89895 | F34: =SUMIFS('Cleaned Data'!$M:$M,'Cleaned Data'!$H:$H,$B34,'Cleaned Data'!$C:$C,F$29) -> 30995 | G34: =SUMIFS('Cleaned Data'!$M:$M,'Cleaned Data'!$H:$H,$B34,'Cleaned Data'!$C:$C,G$29) -> 78720 | H34: =SUMIFS('Cleaned Data'!$M:$M,'Cleaned Data'!$H:$H,$B34,'Cleaned Data'!$C:$C,H$29) -> 70460 | I34: =SUMIFS('Cleaned Data'!$M:$M,'Cleaned Data'!$H:$H,$B34,'Cleaned Data'!$C:$C,I$29) -> 55735 | J34: =SUMIFS('Cleaned Data'!$M:$M,'Cleaned Data'!$H:$H,$B34,'Cleaned Data'!$C:$C,J$29) -> 98630 | K34: =SUMIFS('Cleaned Data'!$M:$M,'Cleaned Data'!$H:$H,$B34,'Cleaned Data'!$C:$C,K$29) -> 38755 | ... N34: =SUMIFS('Cleaned Data'!$M:$M,'Cleaned Data'!$H:$H,$B34,'Cleaned Data'!$C:$C,N$29) -> 110585 | O34: =SUM(Table8[[#This Row],[JAN]:[DEC]]) -> 854495

Sheet Sheet1
A4: Row Labels | B4: Sum of Total Revenue (PKR) | D4: Row Labels | E4: Sum of Total Revenue (PKR)
A5: Groceries | B5: 854495 | D5: Quetta | E5: 5230650
A6: Sports | B6: 3124595 | D6: Peshawar | E6: 5312700
A7: Clothing | B7: 3323600 | D7: Faisalabad | E7: 5745085
A8: Home Appliances | B8: 12344050 | D8: Rawalpindi | E8: 6559530
A9: Electronics | B9: 33322000 | D9: Multan | E9: 6952720
A10: Grand Total | B10: 52968740 | D10: Karachi | E10: 7566335
D11: Islamabad | E11: 7690565
A12: Row Labels | B12: Sum of Total Revenue (PKR) | D12: Lahore | E12: 7911155
A13: Bilal Hussain | B13: 8698130 | D13: Grand Total | E13: 52968740
A14: Nadia Iqbal | B14: 7225110
A15: Ayesha Siddiqui | B15: 6054305
A16: Sara Khan | B16: 6046970
A17: Fatima Malik | B17: 5657955
A18: Grand Total | B18: 33682470
A20: Sum of Total Revenue (PKR) | B20: Sum of Profit (PKR)
A21: 52968740 | B21: 9129880

Sheet Pivot Tables
E5: Delivery Status | F5: Payment Method
E6: Row Labels | F6: Bank Transfer | G6: Cash | H6: Credit Card | I6: Debit Card | J6: EasyPaisa | K6: JazzCash | L6: Grand Total
E7: Cancelled | F7: 6 | G7: 5 | H7: 5 | I7: 6 | J7: 6 | K7: 7 | L7: 35
E8: Delivered | F8: 44 | G8: 48 | H8: 51 | I8: 43 | J8: 49 | K8: 55 | L8: 290
B9: Row Labels | C9: Sum of Total Revenue (PKR) | E9: Pending | F9: 19 | G9: 10 | H9: 15 | I9: 10 | J9: 14 | K9: 16 | L9: 84
B10: Faisalabad | C10: 5745085 | E10: Returned | F10: 3 | G10: 3 | H10: 3 | I10: 2 | J10: 6 | K10: 1 | L10: 18
B11: Clothing | C11: 430300 | E11: Shipped | F11: 18 | G11: 9 | H11: 11 | I11: 14 | J11: 8 | K11: 13 | L11: 73
B12: Ayesha Siddiqui | C12: 14000 | E12: Grand Total | F12: 90 | G12: 75 | H12: 85 | I12: 75 | J12: 83 | K12: 92 | L12: 500
B13: Bilal Hussain | C13: 27000
B14: Fatima Malik | C14: 188800
B15: Hassan Mirza | C15: 19950
B16: Kamran Sheikh | C16: 136700
B17: Nadia Iqbal | C17: 14600
B18: Sara Khan | C18: 17100 | E18: Row Labels | F18: Revenue (PKR) | G18: Profit (PKR)
B19: Usman Raza | C19: 12150 | E19: Jan | F19: 2460695 | G19: 552595
B20: Electronics | C20: 3858500 | E20: Feb | F20: 3132285 | G20: 856405
B21: Groceries | C21: 101095 | E21: Mar | F21: 5513990 | G21: 878230
B22: Home Appliances | C22: 992150 | E22: Apr | F22: 4273160 | G22: 321160
B23: Sports | C23: 363040 | E23: May | F23: 5450265 | G23: 861585
B24: Islamabad | C24: 7690565 | E24: Jun | F24: 4061155 | G24: 971535
B25: Karachi | C25: 7566335 | E25: Jul | F25: 4147310 | G25: 800830
B26: Lahore | C26: 7911155 | E26: Aug | F26: 4014755 | G26: 688915
B27: Multan | C27: 6952720 | E27: Sep | F27: 6048320 | G27: 1083020
B28: Peshawar | C28: 5312700 | E28: Oct | F28: 4181445 | G28: 802725
B29: Quetta | C29: 5230650 | E29: Nov | F29: 4251165 | G29: 762365
B30: Rawalpindi | C30: 6559530 | E30: Dec | F30: 5434195 | G30: 550515
B31: Grand Total | C31: 52968740 | E31: Grand Total | F31: 52968740 | G31: 9129880

Sheet Dashboard
B5: =SUM(Table1[Total Revenue (PKR)]) -> 52968740 | D5: =SUM(Table1[Profit (PKR)]) -> 9129880
G6: =Table1[[#Totals],[Profit (PKR)]]/Table1[[#Totals],[Total Revenue (PKR)]] -> 0.17236355
B11: =INDEX(Table3[[#All],[Region]],MATCH(MAX(Table3[[#All],[Total Revenue]]),Table3[[#All],[Total Revenue]],0)) -> Lahore | E11: =INDEX(Table2[[#All],[Salesperson]],MATCH(MAX(Table2[[#All],[Total Revenue ]]),Table2[[#All],[Total Revenue ]],0)) -> Bilal Hussain | H11: =COUNTIFS(Table1[Delivery Status],"Delivered") -> 290

Sheet Report
B22: # | C22: Metric | D22: Value | E22: Interpretation
B23: 1 | C23: Total Revenue | D23: PKR 52.9M | E23: Overall business performance
B24: 2 | C24: Total Profit | D24: PKR 9.1M | E24: 17.2% of total revenue
B25: 3 | C25: Top Region by Revenue | D25: Lahore | E25: PKR 7.9M but lowest margin
B26: 4 | C26: Peak Revenue Month | D26: September | E26: 6.0M -- Highest Monthly revenue
B27: 5 | C27: Top Salesperson | D27: Bilal Hussain | E27: PKR 1.4M profit
B28: 6 | C28: Most Orders | D28: Nadia Iqbal | E28: 66 orders handled
B29: 7 | C29: Dominant Category | D29: Electronics | E29: 63% of total revenue
B30: 8 | C30: Delivery Rate | D30: 0.58 | E30: 290 of 500 orders delivered
